pathpartout/__init__.py
pathpartout/api/__init__.py
pathpartout/api/aggregate.py
pathpartout/api/auto_arbo.py
pathpartout/api/config_folders.py
pathpartout/api/label.py
pathpartout/api/tree.py
pathpartout/api/tree_path.py
pathpartout/application/__init__.py
pathpartout/application/entities/__init__.py
pathpartout/application/entities/conceptual_path.py
pathpartout/application/entities/configuration.py
pathpartout/application/entities/label.py
pathpartout/application/entities/tree_architecture.py
pathpartout/application/entities/tree_node.py
pathpartout/application/presenter/__init__.py
pathpartout/application/presenter/tree_presenter.py
pathpartout/application/use_cases/__init__.py
pathpartout/application/use_cases/aggregate_getter.py
pathpartout/application/use_cases/config_folders_reader.py
pathpartout/application/use_cases/config_path_finder.py
pathpartout/application/use_cases/config_reader.py
pathpartout/application/use_cases/info_getter.py
pathpartout/application/use_cases/path_finder.py
pathpartout/application/use_cases/tree_base_builder.py
pathpartout/application/use_cases/tree_base_getter.py
pathpartout/application/use_cases/tree_builder.py
pathpartout/infrastructure/__init__.py
pathpartout/infrastructure/path_tree_presenter.py
pathpartout-2.0.1.dist-info/LICENCE.txt
pathpartout-2.0.1.dist-info/METADATA
pathpartout-2.0.1.dist-info/WHEEL
pathpartout-2.0.1.dist-info/top_level.txt
pathpartout-2.0.1.dist-info/RECORD
