Metadata-Version: 2.1
Name: pathpartout
Version: 2.0.1
Summary: Path Parser
Author-email: Cube Creative <development@cube-creative.com>
License-File: LICENCE.txt
Requires-Dist: PyYAML<7,>=5
